<TextureAtlas imagePath="sprites.png">
	<SubTexture name="Fall (32x32).png" x="261" y="188" width="24" height="26"/>
	<SubTexture name="Idle (32x32)_01.png" x="299" y="123" width="23" height="24"/>
	<SubTexture name="Idle (32x32)_02.png" x="287" y="189" width="23" height="24"/>
	<SubTexture name="Idle (32x32)_03.png" x="287" y="189" width="23" height="24"/>
	<SubTexture name="Idle (32x32)_04.png" x="287" y="162" width="23" height="25"/>
	<SubTexture name="Idle (32x32)_05.png" x="287" y="162" width="23" height="25"/>
	<SubTexture name="Idle (32x32)_06.png" x="286" y="216" width="23" height="26"/>
	<SubTexture name="Idle (32x32)_07.png" x="286" y="216" width="23" height="26"/>
	<SubTexture name="Idle (32x32)_08.png" x="286" y="216" width="23" height="26"/>
	<SubTexture name="Idle (32x32)_09.png" x="286" y="216" width="23" height="26"/>
	<SubTexture name="Idle (32x32)_10.png" x="281" y="96" width="23" height="25"/>
	<SubTexture name="Idle (32x32)_11.png" x="281" y="96" width="23" height="25"/>
	<SubTexture name="Idle.png" x="203" y="136" width="43" height="43"/>
	<SubTexture name="Jump (32x32).png" x="261" y="216" width="23" height="28"/>
	<SubTexture name="On (24x8)_01.png" x="0" y="238" width="23" height="8"/>
	<SubTexture name="On (24x8)_02.png" x="42" y="238" width="15" height="8"/>
	<SubTexture name="On (24x8)_03.png" x="59" y="238" width="7" height="8"/>
	<SubTexture name="On (24x8)_04.png" x="25" y="238" width="15" height="8"/>
	<SubTexture name="On (38x38)_01.png" x="203" y="96" width="76" height="38"/>
	<SubTexture name="On (38x38)_02.png" x="156" y="198" width="76" height="38"/>
	<SubTexture name="On (38x38)_03.png" x="78" y="198" width="76" height="38"/>
	<SubTexture name="On (38x38)_04.png" x="0" y="198" width="76" height="38"/>
	<SubTexture name="Run (32x32)_01.png" x="274" y="136" width="23" height="24"/>
	<SubTexture name="Run (32x32)_02.png" x="306" y="96" width="23" height="24"/>
	<SubTexture name="Run (32x32)_03.png" x="306" y="96" width="23" height="24"/>
	<SubTexture name="Run (32x32)_04.png" x="274" y="136" width="23" height="24"/>
	<SubTexture name="Run (32x32)_05.png" x="234" y="207" width="25" height="24"/>
	<SubTexture name="Run (32x32)_06.png" x="234" y="207" width="25" height="24"/>
	<SubTexture name="Run (32x32)_07.png" x="261" y="162" width="24" height="24"/>
	<SubTexture name="Run (32x32)_08.png" x="248" y="136" width="24" height="24"/>
	<SubTexture name="Run (32x32)_09.png" x="248" y="136" width="24" height="24"/>
	<SubTexture name="Run (32x32)_10.png" x="261" y="162" width="24" height="24"/>
	<SubTexture name="Run (32x32)_11.png" x="234" y="181" width="25" height="24"/>
	<SubTexture name="Run (32x32)_12.png" x="234" y="181" width="25" height="24"/>
	<SubTexture name="ground_grass.png" x="0" y="0" width="380" height="94"/>
	<SubTexture name="ground_grass_small.png" x="0" y="96" width="201" height="100"/>
</TextureAtlas>